[
  {"date": "2026-01-25", "adjective": "RAGING", "noun": "DRAGON"},
  {"date": "2026-01-26", "adjective": "MASSIVE", "noun": "MINOTAUR"},
  {"date": "2026-01-27", "adjective": "FIERCE", "noun": "GRIFFIN"},
  {"date": "2026-01-28", "adjective": "ANCIENT", "noun": "WYVERN"},
  {"date": "2026-01-29", "adjective": "VENOMOUS", "noun": "BASILISK"},
  {"date": "2026-01-30", "adjective": "SINISTER", "noun": "DEMON"},
  {"date": "2026-01-31", "adjective": "BLOODTHIRSTY", "noun": "VAMPIRE"},
  {"date": "2026-02-01", "adjective": "TERRIFYING", "noun": "WEREWOLF"},
  {"date": "2026-02-02", "adjective": "DEADLY", "noun": "SPHINX"},
  {"date": "2026-02-03", "adjective": "SLAUGHTERING", "noun": "ORC"},
  {"date": "2026-02-04", "adjective": "BRUTAL", "noun": "TROLL"},
  {"date": "2026-02-05", "adjective": "RAVAGING", "noun": "GARGOYLE"},
  {"date": "2026-02-06", "adjective": "MALEVOLENT", "noun": "WRAITH"},
  {"date": "2026-02-07", "adjective": "DESTRUCTIVE", "noun": "GOLEM"},
  {"date": "2026-02-08", "adjective": "SADISTIC", "noun": "HARPY"},
  {"date": "2026-02-09", "adjective": "CRUEL", "noun": "CYCLOPS"},
  {"date": "2026-02-10", "adjective": "FEROCIOUS", "noun": "CHIMERA"},
  {"date": "2026-02-11", "adjective": "MURDEROUS", "noun": "GHOUL"},
  {"date": "2026-02-12", "adjective": "VICIOUS", "noun": "HYDRA"},
  {"date": "2026-02-13", "adjective": "SINISTER", "noun": "LICH"},
  {"date": "2026-02-14", "adjective": "RUTHLESS", "noun": "BANSHEE"},
  {"date": "2026-02-15", "adjective": "SAVAGE", "noun": "WENDIGO"},
  {"date": "2026-02-16", "adjective": "MALICIOUS", "noun": "SPECTER"},
  {"date": "2026-02-17", "adjective": "DEVASTATING", "noun": "BEHEMOTH"},
  {"date": "2026-02-18", "adjective": "BLOODY", "noun": "ZOMBIE"},
  {"date": "2026-02-19", "adjective": "TERRIFYING", "noun": "PHANTOM"},
  {"date": "2026-02-20", "adjective": "RAMPAGING", "noun": "OGRE"},
  {"date": "2026-02-21", "adjective": "DEADLY", "noun": "WIGHT"},
  {"date": "2026-02-22", "adjective": "FIENDISH", "noun": "IMP"},
  {"date": "2026-02-23", "adjective": "CURSED", "noun": "SKELETON"}
]
